langsearch/__init__.py
langsearch/exceptions.py
langsearch/utils.py
langsearch/chains/__init__.py
langsearch/chains/hyde.py
langsearch/chains/qa.py
langsearch/middlewares/__init__.py
langsearch/middlewares/spidermiddlewares.py
langsearch/pipelines/__init__.py
langsearch/pipelines/base.py
langsearch/pipelines/detect.py
langsearch/pipelines/dryrun.py
langsearch/pipelines/common/__init__.py
langsearch/pipelines/common/index.py
langsearch/pipelines/common/inscriptis.py
langsearch/pipelines/common/language.py
langsearch/pipelines/common/python_readability.py
langsearch/pipelines/common/readability_js.py
langsearch/pipelines/common/storeitem.py
langsearch/pipelines/common/summary_index.py
langsearch/pipelines/common/textsplitter.py
langsearch/pipelines/common/tika.py
langsearch/pipelines/common/trafilatura.py
langsearch/pipelines/common/mixins/__Init__.py
langsearch/pipelines/common/mixins/summary.py
langsearch/pipelines/common/mixins/weaviatedb.py
langsearch/pipelines/types/__init__.py
langsearch/pipelines/types/assemble.py
langsearch/pipelines/types/enumerations.py
langsearch/pipelines/types/audio/__init__.py
langsearch/pipelines/types/audio/audiopipeline.py
langsearch/pipelines/types/audio/whisper.py
langsearch/pipelines/types/html/__init__.py
langsearch/pipelines/types/html/fix_html.py
langsearch/pipelines/types/html/htmlpipeline.py
langsearch/pipelines/types/image/__init__.py
langsearch/pipelines/types/image/imageindex.py
langsearch/pipelines/types/image/imagepipeline.py
langsearch/pipelines/types/image/resize.py
langsearch/pipelines/types/other/__init__.py
langsearch/pipelines/types/other/otherpipeline.py
langsearch/pipelines/types/plaintext/__init__.py
langsearch/pipelines/types/plaintext/plaintextpipeline.py
langsearch/spiders/__init__.py
langsearch/spiders/filespider.py
langsearch/spiders/webspider.py
langsearch-0.1.9.dist-info/METADATA
langsearch-0.1.9.dist-info/WHEEL
langsearch-0.1.9.dist-info/RECORD
